README.rst
setup.cfg
setup.py
i3_config_builder.egg-info/PKG-INFO
i3_config_builder.egg-info/SOURCES.txt
i3_config_builder.egg-info/dependency_links.txt
i3_config_builder.egg-info/entry_points.txt
i3_config_builder.egg-info/requires.txt
i3_config_builder.egg-info/top_level.txt
i3cfgbuild/__init__.py
i3cfgbuild/main.py