Metadata-Version: 1.0
Name: i3-config-builder
Version: 0.1
Summary: Command Line i3 config builder
Home-page: https://github.com/brileb73/i3-config-builder
Author: Brian LeBlanc
Author-email: brileb73@gmail.com
License: MIT
Platform: UNKNOWN
